slardar/__init__.py
slardar/pool.py
slardar/py.typed
slardar/utils.py
slardar-0.0.1.dist-info/METADATA
slardar-0.0.1.dist-info/WHEEL
slardar-0.0.1.dist-info/top_level.txt
slardar-0.0.1.dist-info/RECORD
