Metadata-Version: 2.1
Name: slardar
Version: 0.0.1
Summary: execution scheduler for asyncio
Home-page: https://github.com/lexdene/slardar
Requires-Python: >=3.10
